zd/__init__.py
zd/boop/__init__.py
zd/boop/aws/__init__.py
zd/boop/aws/sqs.py
zd/test/__init__.py
zd/test/aws/__init__.py
zd/test/aws/sqs.py
zd/test/envconfig.py
zd/test/metrics/__init__.py
zd/test/mock/__init__.py
zd/test/mock/aws.py
zd/test/timehelp/__init__.py
zd/test/tools/__init__.py
zd/test/tools/tests.py
zd.testt-0.1.0.dist-info/WHEEL
zd.testt-0.1.0.dist-info/METADATA
zd.testt-0.1.0.dist-info/RECORD
